setaire/__init__.py
setaire/command.py
setaire/main.py
setaire-0.0.1.dist-info/METADATA
setaire-0.0.1.dist-info/WHEEL
setaire-0.0.1.dist-info/top_level.txt
setaire-0.0.1.dist-info/RECORD
